README.md
setup.py
pulumi_acme/__init__.py
pulumi_acme/_inputs.py
pulumi_acme/_utilities.py
pulumi_acme/certificate.py
pulumi_acme/outputs.py
pulumi_acme/provider.py
pulumi_acme/pulumi-plugin.json
pulumi_acme/py.typed
pulumi_acme/registration.py
pulumi_acme.egg-info/PKG-INFO
pulumi_acme.egg-info/SOURCES.txt
pulumi_acme.egg-info/dependency_links.txt
pulumi_acme.egg-info/not-zip-safe
pulumi_acme.egg-info/requires.txt
pulumi_acme.egg-info/top_level.txt
pulumi_acme/config/__init__.py
pulumi_acme/config/vars.py