Metadata-Version: 2.1
Name: pulumi-acme
Version: 0.0.0
Summary: A Pulumi package for creating and managing acme cloud resources.
Home-page: https://www.pulumi.com
License: Apache-2.0
Project-URL: Repository, https://github.com/Tolyar/pulumi-acme
Keywords: pulumi acme category/cloud
